LICENSE
MANIFEST.in
README.rst
setup.py
mailsnake/__init__.py
mailsnake/exceptions.py
mailsnake/mailsnake.py
mailsnake.egg-info/PKG-INFO
mailsnake.egg-info/SOURCES.txt
mailsnake.egg-info/dependency_links.txt
mailsnake.egg-info/requires.txt
mailsnake.egg-info/top_level.txt
mailsnake.egg-info/zip-safe