Metadata-Version: 1.0
Name: mailsnake
Version: 1.5.0
Summary: MailChimp API v1.3, STS, Export, Mandrill wrapper for Python.
Home-page: https://github.com/michaelhelmick/python-mailsnake
Author: John-Kim Murphy
Author-email: UNKNOWN
License: UNKNOWN
Download-URL: http://pypi.python.org/pypi/mailsnake/
Keywords: mailsnake mailchimp api wrapper export mandrill sts 1.3
Platform: UNKNOWN
Classifier: Development Status :: 5 - Production/Stable
Classifier: Intended Audience :: Developers
Classifier: License :: OSI Approved :: MIT License
Classifier: Natural Language :: English
Classifier: Operating System :: OS Independent
Classifier: Programming Language :: Python
Classifier: Topic :: Software Development :: Libraries :: Python Modules
